setup.cfg
setup.py
bin/carlcm-bootstrap-council
bin/carlcm-cluster-role
bin/carlcm-counselor
bin/carlcm-run-role
carlcm/__init__.py
carlcm/configuration_manager.py
carlcm/counselor.py
carlcm/internal_utils.py
carlcm/splitvers.py
carlcm.egg-info/PKG-INFO
carlcm.egg-info/SOURCES.txt
carlcm.egg-info/dependency_links.txt
carlcm.egg-info/requires.txt
carlcm.egg-info/top_level.txt
carlcm/actions/__init__.py
carlcm/actions/action_module.py
carlcm/actions/aws.py
carlcm/actions/aws_mock.py
carlcm/actions/core.py
carlcm/actions/core_mock.py
carlcm/modules/__init__.py
carlcm/modules/base.py
carlcm/modules/consul.py
carlcm/modules/docker.py
carlcm/modules/example.py
carlcm/roles/__init__.py
carlcm/roles/example.py
carlcm/roles/instance_role.py
carlcm/roles/meta_role.py
tests/local-integration.py
tests/local-modules.py