Metadata-Version: 1.1
Name: carlcm
Version: 0.1.15
Summary: CarlCM
Home-page: https://github.com/cjmackey/carlcm
Author: Carl J Mackey
Author-email: carljmackey@gmail.com
License: UNKNOWN
Platform: UNKNOWN
Classifier: Development Status :: 1 - Planning
Classifier: Intended Audience :: Developers
Classifier: Intended Audience :: Information Technology
Classifier: Intended Audience :: System Administrators
Classifier: License :: OSI Approved :: GNU General Public License v3 (GPLv3)
Classifier: Topic :: System :: Installation/Setup
